odoo/addons/web_editor_background_color/README.rst
odoo/addons/web_editor_background_color/__init__.py
odoo/addons/web_editor_background_color/__manifest__.py
odoo/addons/web_editor_background_color/i18n/ca.po
odoo/addons/web_editor_background_color/i18n/es.po
odoo/addons/web_editor_background_color/i18n/fr.po
odoo/addons/web_editor_background_color/i18n/sl.po
odoo/addons/web_editor_background_color/i18n/web_editor_background_color.pot
odoo/addons/web_editor_background_color/readme/CONTRIBUTORS.rst
odoo/addons/web_editor_background_color/readme/CREDITS.rst
odoo/addons/web_editor_background_color/readme/DESCRIPTION.rst
odoo/addons/web_editor_background_color/readme/USAGE.rst
odoo/addons/web_editor_background_color/static/description/icon.png
odoo/addons/web_editor_background_color/static/description/index.html
odoo/addons/web_editor_background_color/static/src/css/background_color.less
odoo/addons/web_editor_background_color/static/src/js/background_color.js
odoo/addons/web_editor_background_color/static/src/lib/bootstrap-colorpicker/bootstrap-colorpicker.css
odoo/addons/web_editor_background_color/static/src/lib/bootstrap-colorpicker/bootstrap-colorpicker.js
odoo/addons/web_editor_background_color/static/src/xml/colorpicker.xml
odoo/addons/web_editor_background_color/templates/assets.xml
odoo11_addon_web_editor_background_color-11.0.1.0.1.dist-info/METADATA
odoo11_addon_web_editor_background_color-11.0.1.0.1.dist-info/WHEEL
odoo11_addon_web_editor_background_color-11.0.1.0.1.dist-info/top_level.txt
odoo11_addon_web_editor_background_color-11.0.1.0.1.dist-info/RECORD
